curious/__init__.py
curious/api.py
curious/count.py
curious/grammar.py
curious/graph.py
curious/parser.py
curious/query.py
curious/related.py
curious/settings.py
curious/urls.py
curious/utils.py
curious/static/curious/dist/curious.css
curious/static/curious/dist/curious.js
curious/static/curious/dist/curious.min.js
curious/static/curious/dist/curious_jst.js
curious/static/curious/lib/angular/.bower.json
curious/static/curious/lib/angular/README.md
curious/static/curious/lib/angular/angular-csp.css
curious/static/curious/lib/angular/angular.js
curious/static/curious/lib/angular/angular.min.js
curious/static/curious/lib/angular/angular.min.js.map
curious/static/curious/lib/angular/bower.json
curious/static/curious/lib/angular-route/.bower.json
curious/static/curious/lib/angular-route/README.md
curious/static/curious/lib/angular-route/angular-route.js
curious/static/curious/lib/angular-route/angular-route.min.js
curious/static/curious/lib/angular-route/angular-route.min.js.map
curious/static/curious/lib/angular-route/bower.json
curious/static/curious/lib/angular-sanitize/.bower.json
curious/static/curious/lib/angular-sanitize/README.md
curious/static/curious/lib/angular-sanitize/angular-sanitize.js
curious/static/curious/lib/angular-sanitize/angular-sanitize.min.js
curious/static/curious/lib/angular-sanitize/angular-sanitize.min.js.map
curious/static/curious/lib/angular-sanitize/bower.json
curious/static/curious/lib/bootstrap/.bower.json
curious/static/curious/lib/bootstrap/Gruntfile.js
curious/static/curious/lib/bootstrap/LICENSE
curious/static/curious/lib/bootstrap/README.md
curious/static/curious/lib/bootstrap/bower.json
curious/static/curious/lib/bootstrap/package.json
curious/static/curious/lib/bootstrap/dist/css/bootstrap-theme.css
curious/static/curious/lib/bootstrap/dist/css/bootstrap-theme.css.map
curious/static/curious/lib/bootstrap/dist/css/bootstrap-theme.min.css
curious-1.2.0.dist-info/METADATA
curious-1.2.0.dist-info/RECORD
curious-1.2.0.dist-info/WHEEL
curious-1.2.0.dist-info/top_level.txt
curious-1.2.0.dist-info/zip-safe
