Metadata-Version: 2.1
Name: curious
Version: 1.2.0
Summary: Graph-based data exploration tool
Home-page: https://github.com/ginkgobioworks/curious
Author: Benjie Chen, Ginkgo Bioworks
Author-email: benjie@ginkgobioworks.com, devs@ginkgobioworks.com
License: MIT
Keywords: graph query django sql curious database ginkgo
Platform: UNKNOWN
Classifier: Development Status :: 5 - Production/Stable
Classifier: Environment :: Web Environment
Classifier: Environment :: Other Environment
Classifier: Framework :: Django :: 1.6
Classifier: Intended Audience :: Developers
Classifier: Intended Audience :: Science/Research
Classifier: License :: OSI Approved :: MIT License
Classifier: Natural Language :: English
Classifier: Operating System :: OS Independent
Classifier: Programming Language :: Python :: 2.7
Classifier: Programming Language :: JavaScript
Classifier: Programming Language :: SQL
Classifier: Topic :: Database
Classifier: Topic :: Internet :: WWW/HTTP :: Indexing/Search
Classifier: Topic :: Internet :: WWW/HTTP :: WSGI :: Application
Classifier: Topic :: Scientific/Engineering :: Information Analysis
Classifier: Topic :: Software Development :: Libraries
Classifier: Topic :: Software Development :: Libraries :: Python Modules
Classifier: Topic :: Text Processing :: General
Requires-Dist: Django (~=1.11)
Requires-Dist: humanize
Requires-Dist: parsimonious (==0.5)
Requires-Dist: parsedatetime (~=1.0)
